README.md
setup.py
gin_demo/__init__.py
gin_demo/ok.py
gin_demo.egg-info/PKG-INFO
gin_demo.egg-info/SOURCES.txt
gin_demo.egg-info/dependency_links.txt
gin_demo.egg-info/top_level.txt